linera-0.0.0.dist-info/METADATA
linera-0.0.0.dist-info/WHEEL
linera/__init__.py
linera-0.0.0.dist-info/RECORD
